partial_s3_to_es/__init__.py
partial_s3_to_es/cli.py
partial_s3_to_es/partial_s3_to_es.py
partial_s3_to_es-0.1.0.dist-info/AUTHORS.rst
partial_s3_to_es-0.1.0.dist-info/LICENSE
partial_s3_to_es-0.1.0.dist-info/METADATA
partial_s3_to_es-0.1.0.dist-info/WHEEL
partial_s3_to_es-0.1.0.dist-info/entry_points.txt
partial_s3_to_es-0.1.0.dist-info/top_level.txt
partial_s3_to_es-0.1.0.dist-info/RECORD
